Metadata-Version: 2.1
Name: nd
Version: 0.2
Summary: A Python library for n-dimensional Earth observation data processing
Home-page: https://github.com/jnhansen/nd
Author: Johannes Hansen
Author-email: johannes.hansen@ed.ac.uk
License: MIT
Keywords: earth observation,satellite data,datacube,remote sensing,geospatial,raster,spacetime
Platform: UNKNOWN
Classifier: Intended Audience :: Science/Research
Classifier: Intended Audience :: Developers
Classifier: Natural Language :: English
Classifier: Programming Language :: Python
Classifier: Programming Language :: Python :: 3.5
Classifier: Programming Language :: Python :: 3.6
Classifier: Programming Language :: Python :: 3.7
Classifier: Programming Language :: Python :: 3.8
